src/AMOLED/video_in_timing_if.sv
`ifndef VIDEO_IN_TIMING_IF_SV
`define VIDEO_IN_TIMING_IF_SV
`timescale 1ns/1ps
`default_nettype none

module video_in_timing_if #(
  parameter int X_W = 11,
  parameter int Y_W = 10
)(
  input  logic           clk,
  input  logic           rst,

  input  logic           vsync,
  input  logic           hsync,
  input  logic           de,
  input  logic [23:0]    rgb,

  output logic           pix_valid,
  output logic [23:0]    pix_rgb,
  output logic [X_W-1:0] x,
  output logic [Y_W-1:0] y,
  output logic           sof,
  output logic           sol,
  output logic           eol,
  output logic           eof
);

  // ----------------------------
  // 1) input sync (1-stage) + edge detect
  //    只做「一級」同步，輸出直接用這級 => pix_valid 延遲 1 拍
  // ----------------------------
  logic vs_q, hs_q, de_q;
  logic [23:0] rgb_q;

  logic vs_d, hs_d, de_d;   // previous of *_q

  always_ff @(posedge clk) begin
    if (rst) begin
      vs_q  <= 1'b0;
      hs_q  <= 1'b0;
      de_q  <= 1'b0;
      rgb_q <= '0;

      vs_d  <= 1'b0;
      hs_d  <= 1'b0;
      de_d  <= 1'b0;
    end else begin
      // stage-1 sync
      vs_q  <= vsync;
      hs_q  <= hsync;
      de_q  <= de;
      rgb_q <= rgb;

      // previous (for edge detect)
      vs_d  <= vs_q;
      hs_d  <= hs_q;
      de_d  <= de_q;
    end
  end

  wire de_rise = (de_q && !de_d);
  wire de_fall = (!de_q && de_d);
  wire vs_rise = (vs_q && !vs_d);

  // ----------------------------
  // 2) pixel outputs (NO extra register stage!)
  // ----------------------------
  // pix_valid/pix_rgb = 同步後的一級暫存 => de 延遲 1 拍
  always_comb begin
    pix_valid = de_q;
    pix_rgb   = rgb_q;
  end

  // ----------------------------
  // 3) x/y counters on active pixels only
  // (保留你原本行為：de_rise 時 x=0，de_q 時 x++)
  // 注意：你原本 y 在 de_rise 會 +1，所以第一行會變 y=1
  // 如果你要第一行 y=0，我下一段也給你改法
  // ----------------------------
  logic last_pix_valid;

  always_ff @(posedge clk) begin
    if (rst) begin
      x <= '0;
      y <= '0;
      last_pix_valid <= 1'b0;
    end else begin
      last_pix_valid <= de_q;

      if (vs_rise) begin
        x <= '0;
        y <= '0;
      end else begin
        if (de_rise) begin
          x <= '0;
          // 你原本行為：每行開始 y++（會讓第一行 y=1）
          y <= y + 1'b1;
        end else if (de_q) begin
          x <= x + 1'b1;
        end
      end
    end
  end

  // ----------------------------
  // 4) SOF/SOL/EOL/EOF pulses
  // (維持你原本 pulse 定義)
  // ----------------------------
  logic sof_armed;
  always_ff @(posedge clk) begin
    if (rst) begin
      sof_armed <= 1'b0;
    end else begin
      if (vs_rise) sof_armed <= 1'b1;
      else if (de_rise && sof_armed) sof_armed <= 1'b0;
    end
  end

  always_ff @(posedge clk) begin
    if (rst) begin
      sof <= 1'b0; sol <= 1'b0; eol <= 1'b0; eof <= 1'b0;
    end else begin
      sof <= (de_rise && sof_armed);
      sol <= (de_rise);

      // 你的 eol 打在 de_fall 的那拍，通常那拍 pix_valid=0（因為 de_q 已經變 0）
      // 先保持你原行為不動
      eol <= (de_fall && last_pix_valid);

      // eof：vs_rise 當拍且上一拍還在有效像素
      eof <= (vs_rise && last_pix_valid);
    end
  end

endmodule

`default_nettype wire
`endif

test/tb_video_in_timing_if.sv
// tb_video_in_timing_if.sv
/*
iverilog -g2012 -Wall -o ./vvp/tb_video.vvp  ./test/tb_video_in_timing_if.sv
vvp ./vvp/tb_video.vvp
gtkwave tb_video.vcd
*/

`include "./src/AMOLED/video_in_timing_if.sv"
`timescale 1ns/1ps
`default_nettype none

module tb_video_in_timing_if;

  // ----------------------------
  // Timing parameters
  // ----------------------------
  localparam int H_ACTIVE = 8;
  localparam int H_BLANK  = 4;
  localparam int V_ACTIVE = 4;
  localparam int V_BLANK  = 2;

  localparam int X_W = 11;
  localparam int Y_W = 10;

  // ----------------------------
  // Clock / Reset
  // ----------------------------
  logic clk = 1'b0;
  always #5 clk = ~clk;

  logic rst;

  // ----------------------------
  // Video inputs
  // ----------------------------
  logic        vsync;
  logic        hsync;
  logic        de;
  logic [23:0] rgb;

  // ----------------------------
  // DUT outputs
  // ----------------------------
  logic           pix_valid;
  logic [23:0]    pix_rgb;
  logic [X_W-1:0] x;
  logic [Y_W-1:0] y;
  logic           sof, sol, eol, eof;

  // ----------------------------
  // Instantiate DUT
  // ----------------------------
  video_in_timing_if #(
    .X_W(X_W),
    .Y_W(Y_W)
  ) dut (
    .clk       (clk),
    .rst       (rst),
    .vsync     (vsync),
    .hsync     (hsync),
    .de        (de),
    .rgb       (rgb),
    .pix_valid (pix_valid),
    .pix_rgb   (pix_rgb),
    .x         (x),
    .y         (y),
    .sof       (sof),
    .sol       (sol),
    .eol       (eol),
    .eof       (eof)
  );

  // ----------------------------
  // Wave dump
  // ----------------------------
  initial begin
    $dumpfile("tb_video.vcd");
    $dumpvars(0, tb_video_in_timing_if);
  end

  // ============================================================
  // TB-side pipelining to match DUT internal sampling:
  // DUT does: de_q <= de; de_d <= de_q; pix_valid <= de_q
  // So TB uses:
  //   de_p1 ~ DUT de_q
  //   de_p2 ~ DUT de_d
  // ============================================================
  logic de_p1, de_p2;
  logic vs_p1, vs_p2;

  logic [31:0] cyc;

  always_ff @(posedge clk) begin
    if (rst) begin
      de_p1 <= 1'b0; de_p2 <= 1'b0;
      vs_p1 <= 1'b0; vs_p2 <= 1'b0;
      cyc   <= 32'd0;
    end else begin
      cyc <= cyc + 1;

      de_p1 <= de;
      de_p2 <= de_p1;

      vs_p1 <= vsync;
      vs_p2 <= vs_p1;
    end
  end

  // TB edges aligned to DUT's de_q/de_d and vs_q/vs_d
  wire tb_de_rise = (de_p1 && !de_p2);
  wire tb_de_fall = (!de_p1 && de_p2);
  wire tb_vs_rise = (vs_p1 && !vs_p2);

  // ============================================================
  // Stimulus
  // ============================================================
  task automatic drive_pixel(input bit v_de, input logic [23:0] v_rgb);
    begin
      de  <= v_de;
      rgb <= v_rgb;
      @(posedge clk);
    end
  endtask

  task automatic drive_line(input int frame_idx, input int line_idx);
    int px;
    logic [23:0] pat;
    begin
      // hsync pulse 1 cycle before line
      hsync <= 1'b1;
      de    <= 1'b0;
      rgb   <= '0;
      @(posedge clk);
      hsync <= 1'b0;

      // front blank
      for (px = 0; px < H_BLANK/2; px++) begin
        drive_pixel(1'b0, 24'h0);
      end

      // active
      for (px = 0; px < H_ACTIVE; px++) begin
        pat = { frame_idx[3:0], line_idx[7:0], px[7:0] };
        drive_pixel(1'b1, pat);
      end

      // back blank
      for (px = 0; px < (H_BLANK - H_BLANK/2); px++) begin
        drive_pixel(1'b0, 24'h0);
      end
    end
  endtask

  task automatic drive_frame(input int frame_idx);
    int ly;
    begin
      // vsync pulse 2 cycles (DUT 用 vs_rise reset)
      vsync <= 1'b0;
      @(posedge clk);
      vsync <= 1'b1;
      @(posedge clk);
      vsync <= 1'b1;
      @(posedge clk);
      vsync <= 1'b0;

      // vertical blank lines
      for (ly = 0; ly < V_BLANK; ly++) begin
        drive_line(frame_idx, -ly-1);
      end

      // active lines
      for (ly = 0; ly < V_ACTIVE; ly++) begin
        drive_line(frame_idx, ly);
      end
    end
  endtask

  // ============================================================
  // Checker (match your current DUT behavior)
  // ============================================================
  int exp_x, exp_y;
  bit exp_in_frame;
  bit seen_first_active;

  always_ff @(posedge clk) begin
    if (rst) begin
      exp_x <= 0;
      exp_y <= 0;
      exp_in_frame <= 0;
      seen_first_active <= 0;
    end else begin
      // frame reset on vs_rise (aligned)
      if (tb_vs_rise) begin
        exp_x <= 0;
        exp_y <= 0;
        exp_in_frame <= 1;
        seen_first_active <= 0;
      end

      // --------------------------------------------------------
      // pix_valid should equal DUT de_q, which TB models as de_p1
      // --------------------------------------------------------
      if (pix_valid !== de_p1) begin
        $display("[ERR] cyc=%0d pix_valid mismatch: dut=%0b exp=%0b (de=%0b de_p1=%0b de_p2=%0b)",
                 cyc, pix_valid, de_p1, de, de_p1, de_p2);
        $fatal;
      end

      // --------------------------------------------------------
      // Line start: tb_de_rise corresponds to DUT de_rise
      // Your DUT behavior: on de_rise: x<=0; y<=y+1 (unless vs_rise)
      // --------------------------------------------------------
      if (tb_de_rise) begin
        exp_x <= 0;

        if (!tb_vs_rise) exp_y <= exp_y + 1;

        // SOL pulse expected on de_rise
        if (sol !== 1'b1) begin
          $display("[ERR] cyc=%0d SOL not asserted on de_rise (sol=%0b)", cyc, sol);
          $fatal;
        end

        // SOF expected on first de_rise after vsync (your sof_armed logic)
        if (exp_in_frame && !seen_first_active) begin
          if (sof !== 1'b1) begin
            $display("[ERR] cyc=%0d SOF expected on first de_rise after vsync, sof=%0b", cyc, sof);
            $fatal;
          end
          seen_first_active <= 1;
        end else begin
          if (sof !== 1'b0) begin
            $display("[ERR] cyc=%0d SOF unexpected (sof=%0b)", cyc, sof);
            $fatal;
          end
        end
      end else begin
        // no de_rise => sol should be 0
        if (sol !== 1'b0) begin
          $display("[ERR] cyc=%0d SOL should be 0 when not de_rise (sol=%0b)", cyc, sol);
          $fatal;
        end
        // sof should be 0 too (except checked above)
        if (sof !== 1'b0) begin
          $display("[ERR] cyc=%0d SOF should be 0 when not first de_rise (sof=%0b)", cyc, sof);
          $fatal;
        end
      end

      // --------------------------------------------------------
      // Active pixel counting:
      // Use de_p1 (aligned with pix_valid) as "active"
      // Your DUT increments x when de_q (de_p1) is 1
      // --------------------------------------------------------
      if (de_p1) begin
        if (x !== exp_x[X_W-1:0]) begin
          $display("[ERR] cyc=%0d X mismatch: dut=%0d exp=%0d", cyc, x, exp_x);
          $fatal;
        end
        if (y !== exp_y[Y_W-1:0]) begin
          $display("[ERR] cyc=%0d Y mismatch: dut=%0d exp=%0d", cyc, y, exp_y);
          $fatal;
        end
        exp_x <= exp_x + 1;
      end

      // --------------------------------------------------------
      // Line end: tb_de_fall corresponds to DUT de_fall
      // Your DUT eol is a bit non-standard; we check it's pulsing near de_fall
      // --------------------------------------------------------
      if (tb_de_fall) begin
        if (eol !== 1'b1) begin
          $display("[WARN] cyc=%0d expected EOL pulse near de_fall, got eol=%0b", cyc, eol);
        end
      end else begin
        if (eol !== 1'b0) begin
          $display("[ERR] cyc=%0d EOL should be 0 when not de_fall (eol=%0b)", cyc, eol);
          $fatal;
        end
      end

      // --------------------------------------------------------
      // EOF: your DUT does eof <= (vs_rise && last_pix_valid)
      // last_pix_valid tracks previous DUT de_q, i.e. previous de_p1
      // In TB, previous de_p1 is de_p2 (because de_p2 <= de_p1)
      // So at tb_vs_rise: eof should equal de_p2
      // --------------------------------------------------------
      if (tb_vs_rise) begin
        if (eof !== de_p2) begin
          $display("[ERR] cyc=%0d EOF mismatch at vs_rise: dut=%0b exp=%0b (de_p2)", cyc, eof, de_p2);
          $fatal;
        end
      end else begin
        if (eof !== 1'b0) begin
          $display("[ERR] cyc=%0d EOF should be 0 when not vs_rise (eof=%0b)", cyc, eof);
          $fatal;
        end
      end

      // Basic sanity: pix_rgb shouldn't be X when valid
      if (pix_valid && (^pix_rgb === 1'bX)) begin
        $display("[ERR] cyc=%0d pix_rgb has X during valid!", cyc);
        $fatal;
      end
    end
  end

  // ============================================================
  // Main
  // ============================================================
  initial begin
    vsync = 0;
    hsync = 0;
    de    = 0;
    rgb   = 0;

    rst = 1;
    repeat (5) @(posedge clk);
    rst = 0;

    drive_frame(0);
    drive_frame(1);

    repeat (20) @(posedge clk);
    $display("[OK] Simulation finished.");
    $finish;
  end

endmodule

`default_nettype wire

tb_video.vcd
$date
	Tue Jan 27 02:19:39 2026
$end
$version
	Icarus Verilog
$end
$timescale
	1ps
$end
$scope module tb_video_in_timing_if $end
$var wire 1 ! tb_de_fall $end
$var wire 1 " tb_de_rise $end
$var wire 1 # tb_vs_rise $end
$var wire 10 $ y [9:0] $end
$var wire 11 % x [10:0] $end
$var wire 1 & sol $end
$var wire 1 ' sof $end
$var wire 1 ( pix_valid $end
$var wire 24 ) pix_rgb [23:0] $end
$var wire 1 * eol $end
$var wire 1 + eof $end
$var parameter 32 , H_ACTIVE $end
$var parameter 32 - H_BLANK $end
$var parameter 32 . V_ACTIVE $end
$var parameter 32 / V_BLANK $end
$var parameter 32 0 X_W $end
$var parameter 32 1 Y_W $end
$var reg 1 2 clk $end
$var reg 32 3 cyc [31:0] $end
$var reg 1 4 de $end
$var reg 1 5 de_p1 $end
$var reg 1 6 de_p2 $end
$var reg 1 7 hsync $end
$var reg 24 8 rgb [23:0] $end
$var reg 1 9 rst $end
$var reg 1 : vs_p1 $end
$var reg 1 ; vs_p2 $end
$var reg 1 < vsync $end
$var reg 1 = exp_in_frame $end
$var integer 32 > exp_x [31:0] $end
$var integer 32 ? exp_y [31:0] $end
$var reg 1 @ seen_first_active $end
$scope module dut $end
$var wire 1 2 clk $end
$var wire 1 4 de $end
$var wire 1 A de_fall $end
$var wire 1 B de_rise $end
$var wire 1 7 hsync $end
$var wire 24 C rgb [23:0] $end
$var wire 1 9 rst $end
$var wire 1 D vs_rise $end
$var wire 1 < vsync $end
$var parameter 32 E X_W $end
$var parameter 32 F Y_W $end
$var reg 1 G de_d $end
$var reg 1 H de_q $end
$var reg 1 + eof $end
$var reg 1 * eol $end
$var reg 1 I hs_d $end
$var reg 1 J hs_q $end
$var reg 1 K last_pix_valid $end
$var reg 24 L pix_rgb [23:0] $end
$var reg 1 ( pix_valid $end
$var reg 24 M rgb_q [23:0] $end
$var reg 1 ' sof $end
$var reg 1 N sof_armed $end
$var reg 1 & sol $end
$var reg 1 O vs_d $end
$var reg 1 P vs_q $end
$var reg 11 Q x [10:0] $end
$var reg 10 R y [9:0] $end
$upscope $end
$scope task drive_frame $end
$upscope $end
$scope task drive_line $end
$upscope $end
$scope task drive_pixel $end
$upscope $end
$upscope $end
$enddefinitions $end
$comment Show the parameter values. $end
$dumpall
b1010 F
b1011 E
b1010 1
b1011 0
b10 /
b100 .
b100 -
b1000 ,
$end
#0
$dumpvars
bx R
bx Q
xP
xO
xN
bx M
bx L
xK
xJ
xI
xH
xG
xD
b0 C
xB
xA
0@
b0 ?
b0 >
0=
0<
x;
x:
19
b0 8
07
x6
x5
04
bx 3
02
x+
x*
bx )
x(
x'
x&
bx %
bx $
x#
x"
x!
$end
#5000
b0 )
b0 L
0(
0A
0B
0D
0#
0!
0"
0G
0I
0O
b0 M
0H
0J
0P
0K
b0 $
b0 R
b0 %
b0 Q
0N
0+
0*
0&
0'
b0 3
0;
0:
06
05
12
#10000
02
#15000
12
#20000
02
#25000
12
#30000
02
#35000
12
#40000
02
#45000
b1 3
09
12
#50000
02
#55000
b10 3
1<
12
#60000
02
#65000
1D
1#
1P
1:
b11 3
12
#70000
02
#75000
0#
0D
17
1=
1;
b100 3
1N
1O
0<
12
#80000
02
#85000
1J
0P
0:
b101 3
07
12
#90000
02
#95000
0;
b110 3
1I
0O
0J
12
#100000
02
#105000
b1111111100000000 8
b1111111100000000 C
14
0I
b111 3
12
#110000
02
#115000
1"
b1111111100000000 )
b1111111100000000 L
1(
1B
b1111111100000001 8
b1111111100000001 C
15
b1000 3
b1111111100000000 M
1H
12
#120000
02
#125000
0B
b1111111100000001 )
b1111111100000001 L
0"
b1111111100000010 8
b1111111100000010 C
1G
b1111111100000001 M
b1 $
b1 R
1K
0N
1&
1'
16
b1001 3
b1 ?
12
